citibox/gcloudlogger/__init__.py
citibox/gcloudlogger/config.py
citibox/gcloudlogger/contrib/__init__.py
citibox/gcloudlogger/contrib/django/__init__.py
citibox/gcloudlogger/contrib/django/django_record_factory.py
citibox/gcloudlogger/contrib/django/middleware/__init__.py
citibox/gcloudlogger/contrib/django/middleware/django_middleware.py
citibox/gcloudlogger/contrib/falcon/__init__.py
citibox/gcloudlogger/contrib/falcon/falcon_record_factory.py
citibox/gcloudlogger/contrib/falcon/middleware/__init__.py
citibox/gcloudlogger/contrib/falcon/middleware/falcon_middleware.py
citibox/gcloudlogger/contrib/fastapi/__init__.py
citibox/gcloudlogger/contrib/fastapi/fastapi_record_factory.py
citibox/gcloudlogger/contrib/fastapi/midleware/__init__.py
citibox/gcloudlogger/contrib/fastapi/midleware/fastapi_middleware.py
citibox/gcloudlogger/src/__init__.py
citibox/gcloudlogger/src/base_context_filter.py
citibox/gcloudlogger/src/base_record.py
citibox/gcloudlogger/src/base_record_factory.py
citibox/gcloudlogger/src/gcloud_formatter.py
citibox/gcloudlogger/src/json_encoder.py
citibox/gcloudlogger/src/log_exception.py
citibox/gcloudlogger/src/middleware/__init__.py
citibox_gcloud_logger-0.5.1.dist-info/METADATA
citibox_gcloud_logger-0.5.1.dist-info/WHEEL
citibox_gcloud_logger-0.5.1.dist-info/top_level.txt
citibox_gcloud_logger-0.5.1.dist-info/RECORD
