Metadata-Version: 2.1
Name: citibox-gcloud-logger
Version: 0.5.1
Summary: Citibox Google cloud logging tools
Home-page: https://citibox.com
Author: Citibox
License: UNKNOWN
Platform: UNKNOWN
Classifier: Programming Language :: Python :: 3
Classifier: License :: OSI Approved :: MIT License
Classifier: Operating System :: OS Independent
Requires-Python: >=3.6
